p929.py
p929-0.6.2.dist-info/METADATA
p929-0.6.2.dist-info/WHEEL
p929-0.6.2.dist-info/top_level.txt
p929-0.6.2.dist-info/RECORD
