Metadata-Version: 2.1
Name: p929
Version: 0.6.2
Summary: Tools for the Project 929 chapter-a-day Tanach learning project
Home-page: https://github.com/EliezerIsrael/p929
Author: Lev Israel
Author-email: lev@sefaria.org
